[
  {
    "commitment": [
      0,
      64,
      7,
      90,
      240,
      117,
      7,
      0,
      0,
      0,
      0,
      0,
      0,
      0,
      0,
      0,
      0,
      0,
      0,
      0,
      0,
      0,
      0,
      0,
      0,
      0,
      0,
      0,
      0,
      0,
      0,
      0
    ],
    "ephemeral_key": [
      134,
      0,
      239,
      23,
      191,
      32,
      31,
      178,
      245,
      41,
      68,
      239,
      158,
      242,
      20,
      155,
      87,
      141,
      77,
      150,
      145,
      19,
      190,
      148,
      19,
      208,
      103,
      137,
      78,
      214,
      75,
      239
    ],
    "ciphertext": [
      71,
      240,
      139,
      191,
      77,
      217,
      135,
      13,
      62,
      8,
      188,
      148,
      214,
      117,
      103,
      132,
      229,
      101,
      145,
      237,
      8,
      88,
      24,
      253,
      211,
      230,
      30,
      80,
      100,
      10,
      24,
      242,
      31,
      52,
      168,
      95,
      18,
      152,
      124,
      58,
      121,
      66,
      203,
      112,
      19,
      129,
      166,
      92,
      239,
      231,
      20,
      56,
      189,
      63,
      199,
      94
    ]
  },
  {
    "commitment": [
      1,
      65,
      100,
      83,
      192,
      199,
      2,
      1,
      1,
      1,
      1,
      1,
      1,
      1,
      1,
      1,
      1,
      1,
      1,
      1,
      1,
      1,
      1,
      1,
      1,
      1,
      1,
      1,
      1,
      1,
      1,
      1
    ],
    "ephemeral_key": [
      72,
      181,
      241,
      25,
      58,
      89,
      127,
      132,
      249,
      183,
      165,
      5,
      233,
      71,
      169,
      219,
      115,
      224,
      193,
      140,
      110,
      17,
      78,
      121,
      133,
      121,
      144,
      182,
      49,
      105,
      83,
      57
    ],
    "ciphertext": [
      43,
      75,
      122,
      21,
      209,
      238,
      85,
      144,
      164,
      129,
      25,
      229,
      73,
      73,
      54,
      78,
      44,
      204,
      171,
      182,
      38,
      116,
      142,
      0,
      250,
      96,
      171,
      52,
      182,
      189,
      248,
      85,
      160,
      129,
      125,
      143,
      138,
      39,
      169,
      66,
      209,
      174,
      21,
      42,
      20,
      117,
      125,
      88,
      173,
      143,
      64,
      89,
      196,
      27,
      24,
      56
    ]
  },
  {
    "commitment": [
      2,
      2,
      166,
      9,
      51,
      177,
      7,
      2,
      2,
      2,
      2,
      2,
      2,
      2,
      2,
      2,
      2,
      2,
      2,
      2,
      2,
      2,
      2,
      2,
      2,
      2,
      2,
      2,
      2,
      2,
      2,
      2
    ],
    "ephemeral_key": [
      239,
      11,
      109,
      17,
      35,
      124,
      19,
      215,
      146,
      77,
      247,
      161,
      151,
      27,
      53,
      24,
      161,
      208,
      116,
      106,
      234,
      131,
      156,
      62,
      59,
      133,
      242,
      31,
      205,
      217,
      49,
      164
    ],
    "ciphertext": [
      249,
      2,
      139,
      160,
      196,
      104,
      157,
      88,
      5,
      221,
      90,
      134,
      237,
      223,
      118,
      123,
      127,
      102,
      182,
      151,
      75,
      139,
      234,
      176,
      203,
      144,
      208,
      248,
      180,
      170,
      234,
      192,
      54,
      60,
      141,
      197,
      44,
      208,
      142,
      33,
      1,
      44,
      31,
      95,
      164,
      11,
      108,
      202,
      208,
      36,
      36,
      211,
      118,
      228,
      33,
      103
    ]
  }
]